safegym/__init__.py
safegym/envs/Satellite.py
safegym/envs/Satellite_SE2.py
safegym/envs/Satellite_mujoco.py
safegym/envs/Satellite_rot.py
safegym/envs/Satellite_tra.py
safegym/envs/Snake_v0.py
safegym/envs/__init__.py
safegym/envs/assets/__init__.py
safegym/models/__init__.py
safegym/models/sac.py
safegym/models/sqrl.py
safegym/models/nets/__init__.py
safegym/models/nets/nets.py
safegym/models/replaybuffer/__init__.py
safegym/models/replaybuffer/replaybuffer.py
safegym-0.14.dist-info/METADATA
safegym-0.14.dist-info/WHEEL
safegym-0.14.dist-info/top_level.txt
safegym-0.14.dist-info/RECORD
