Metadata-Version: 2.1
Name: safegym
Version: 0.14
Summary: Gymnasium Compatible Safe RL Environments
Home-page: https://github.com/spbisc97/SafeGym
Author: Simone Rotondi
Author-email: rotondi97simone@gmail.com
Classifier: Programming Language :: Python :: 3
Requires-Dist: numpy >=1.23
Requires-Dist: gymnasium
